jupyter_twitter/__init__.py
jupyter_twitter/_version.py
jupyter_twitter/handlers.py
jupyter_twitter/tests/__init__.py
jupyter_twitter/tests/test_handlers.py
jupyter_twitter-0.0.2.data/data/etc/jupyter/jupyter_notebook_config.d/jupyter_twitter.json
jupyter_twitter-0.0.2.data/data/etc/jupyter/jupyter_server_config.d/jupyter_twitter.json
jupyter_twitter-0.0.2.data/data/share/jupyter/labextensions/@datalayer/jupyter-twitter/build_log.json
jupyter_twitter-0.0.2.data/data/share/jupyter/labextensions/@datalayer/jupyter-twitter/package.json
jupyter_twitter-0.0.2.data/data/share/jupyter/labextensions/@datalayer/jupyter-twitter/schemas/@datalayer/jupyter-aws/package.json.orig
jupyter_twitter-0.0.2.data/data/share/jupyter/labextensions/@datalayer/jupyter-twitter/schemas/@datalayer/jupyter-aws/plugin.json
jupyter_twitter-0.0.2.data/data/share/jupyter/labextensions/@datalayer/jupyter-twitter/static/design_icons_lib_index_js.cae868cc022ddf18d113.js
jupyter_twitter-0.0.2.data/data/share/jupyter/labextensions/@datalayer/jupyter-twitter/static/design_icons_lib_index_js.cae868cc022ddf18d113.js.map
jupyter_twitter-0.0.2.data/data/share/jupyter/labextensions/@datalayer/jupyter-twitter/static/lib_index_js.8f95b61b59acc237d450.js
jupyter_twitter-0.0.2.data/data/share/jupyter/labextensions/@datalayer/jupyter-twitter/static/lib_index_js.8f95b61b59acc237d450.js.map
jupyter_twitter-0.0.2.data/data/share/jupyter/labextensions/@datalayer/jupyter-twitter/static/remoteEntry.b6092ee64cdf986eeb17.js
jupyter_twitter-0.0.2.data/data/share/jupyter/labextensions/@datalayer/jupyter-twitter/static/remoteEntry.b6092ee64cdf986eeb17.js.map
jupyter_twitter-0.0.2.data/data/share/jupyter/labextensions/@datalayer/jupyter-twitter/static/style.js
jupyter_twitter-0.0.2.data/data/share/jupyter/labextensions/@datalayer/jupyter-twitter/static/style_index_js.859b9929c33397270eb1.js
jupyter_twitter-0.0.2.data/data/share/jupyter/labextensions/@datalayer/jupyter-twitter/static/style_index_js.859b9929c33397270eb1.js.map
jupyter_twitter-0.0.2.dist-info/METADATA
jupyter_twitter-0.0.2.dist-info/WHEEL
jupyter_twitter-0.0.2.dist-info/licenses/LICENSE
jupyter_twitter-0.0.2.dist-info/RECORD
